repl_uploader/__init__.py
repl_uploader/masterRR.py
repl_uploader/replicon.py
repl_uploader/replicon_ws.py
repl_uploader/pyqt/CamReader.py
repl_uploader/pyqt/Sefaz.py
repl_uploader/pyqt/__init__.py
repl_uploader/pyqt/qrcode.py
repl_uploader/utils/__init__.py
repl_uploader/utils/ex_rates.py
repl_uploader/utils/pdf_creator.py
repl_uploader/utils/token_generator.py
repl_uploader-2.2.7.dist-info/LICENSE
repl_uploader-2.2.7.dist-info/METADATA
repl_uploader-2.2.7.dist-info/WHEEL
repl_uploader-2.2.7.dist-info/top_level.txt
repl_uploader-2.2.7.dist-info/RECORD
