Metadata-Version: 2.1
Name: repl-uploader
Version: 2.2.7
Summary: Collection of scripts to upload Replicon expenses
Home-page: https://github.com/thig0w/replicon
Author: Thiago Weidman
Author-email: tw@weidman.com.br
Classifier: Programming Language :: Python :: 3
Classifier: License :: OSI Approved :: GNU General Public License v3 (GPLv3)
Classifier: Operating System :: Microsoft :: Windows
Classifier: Development Status :: 4 - Beta 
License-File: LICENSE
Requires-Dist: selenium
Requires-Dist: PyMuPDF
Requires-Dist: Pillow
Requires-Dist: PyQt5
Requires-Dist: pyzbar
Requires-Dist: opencv-python
Requires-Dist: xlwings
Requires-Dist: reportlab
Requires-Dist: PyPDF2 (>=1.26.0)
Requires-Dist: simplejson (>=3.17.0)
Requires-Dist: requests (>=2.23.0)
Requires-Dist: pdfkit (>=0.6.1)
Requires-Dist: chromedriver-binary (==86.0.4240.22.0)
Requires-Dist: isoweek
Requires-Dist: appdirs
